colcon_notification/__init__.py
colcon_notification/desktop_notification/__init__.py
colcon_notification/desktop_notification/notify2.py
colcon_notification/desktop_notification/notify_send.py
colcon_notification/desktop_notification/terminal_notifier.py
colcon_notification/desktop_notification/win32.py
colcon_notification/desktop_notification/image/__init__.py
colcon_notification/desktop_notification/image/colcon-abort.ico
colcon_notification/desktop_notification/image/colcon-failure.ico
colcon_notification/desktop_notification/image/colcon-success.ico
colcon_notification/desktop_notification/image/colcon-warning.ico
colcon_notification/event_handler/__init__.py
colcon_notification/event_handler/status.py
colcon_notification/event_handler/terminal_title.py
colcon_notification/event_handler/desktop_notification/__init__.py
colcon_notification-0.2.15.data/data/share/colcon_notification/colcon-terminal-notifier.app/Contents/Info.plist
colcon_notification-0.2.15.data/data/share/colcon_notification/colcon-terminal-notifier.app/Contents/PkgInfo
colcon_notification-0.2.15.data/data/share/colcon_notification/colcon-terminal-notifier.app/Contents/MacOS/colcon-terminal-notifier
colcon_notification-0.2.15.data/data/share/colcon_notification/colcon-terminal-notifier.app/Contents/Resources/colcon.icns
colcon_notification-0.2.15.data/data/share/colcon_notification/colcon-terminal-notifier.app/Contents/Resources/en.lproj/Credits.rtf
colcon_notification-0.2.15.data/data/share/colcon_notification/colcon-terminal-notifier.app/Contents/Resources/en.lproj/InfoPlist.strings
colcon_notification-0.2.15.data/data/share/colcon_notification/colcon-terminal-notifier.app/Contents/Resources/en.lproj/MainMenu.nib
colcon_notification-0.2.15.dist-info/LICENSE
colcon_notification-0.2.15.dist-info/METADATA
colcon_notification-0.2.15.dist-info/WHEEL
colcon_notification-0.2.15.dist-info/entry_points.txt
colcon_notification-0.2.15.dist-info/top_level.txt
colcon_notification-0.2.15.dist-info/RECORD
